lib_cidr_trie/__init__.py
lib_cidr_trie/cidr_node.py
lib_cidr_trie/cidr_trie.py
lib_cidr_trie/cidr_tries.py
lib_cidr_trie/py.typed
lib_cidr_trie/tests/__init__.py
lib_cidr_trie/tests/test_cidr_trie.py
lib_cidr_trie-1.2.11.dist-info/licenses/LICENSE.txt
lib_cidr_trie-1.2.11.dist-info/METADATA
lib_cidr_trie-1.2.11.dist-info/WHEEL
lib_cidr_trie-1.2.11.dist-info/top_level.txt
lib_cidr_trie-1.2.11.dist-info/RECORD
