Metadata-Version: 2.4
Name: lib_cidr_trie
Version: 1.2.11
Summary: Contains a trie of prefixes for fast lookups
Author-email: Justin Furuness <jfuruness@gmail.com>
License: Copyright 2020 Justin Furuness
Project-URL: homepage, https://github.com/jfuruness/lib_cidr_trie.git
Keywords: Furuness,prefix,cidr,inet,trie,cidr-trie,roas,roas-trie,ROAs,ROAs-trie,BGP,Hijack,ROA,ROV
Classifier: Programming Language :: Python :: 3.10
Classifier: Programming Language :: Python :: 3.11
Classifier: Programming Language :: Python :: 3.12
Classifier: Programming Language :: Python :: 3.13
Classifier: Programming Language :: Python :: 3.14
Classifier: Programming Language :: Python :: Implementation :: CPython
Classifier: Programming Language :: Python :: Implementation :: PyPy
Classifier: Environment :: Console
Classifier: License :: OSI Approved :: BSD License
Classifier: Intended Audience :: Developers
Classifier: Operating System :: POSIX :: Linux
Classifier: Operating System :: MacOS
Classifier: Operating System :: MacOS :: MacOS X
Classifier: Topic :: Security
Requires-Python: >=3.10
License-File: LICENSE.txt
Provides-Extra: test
Requires-Dist: pytest==9.0.2; extra == "test"
Requires-Dist: pre-commit==4.5.1; extra == "test"
Requires-Dist: mypy==1.19.1; extra == "test"
Requires-Dist: tox==4.34.1; extra == "test"
Requires-Dist: ruff==0.14.13; extra == "test"
Dynamic: license-file
